{
  "id": "mysteries-b1-040",
  "category": "mysteries",
  "level": "B1",
  "sentences": [
    {
      "arabic": "وَجَدَ مُحَمَّدٌ كِيسًا أَمَامَ بَابِ الْبَيْتِ.",
      "translation": "Muhammed je pronašao vrećicu ispred kućnih vrata.",
      "translationEn": "Muhammad found a bag in front of the house door.",
      "words": [
        {
          "w": "وَجَدَ",
          "lemma": "وَجَدَ يَجِدُ"
        },
        {
          "w": "كِيسًا",
          "lemma": "كِيسٌ / أَكْيَاسٌ"
        },
        {
          "w": "أَمَامَ",
          "lemma": "أَمَامَ"
        },
        {
          "w": "بَابِ",
          "lemma": "بَابٌ / أَبْوَابٌ"
        },
        {
          "w": "الْبَيْتِ",
          "lemma": "بَيْتٌ / بُيُوتٌ"
        }
      ]
    },
    {
      "arabic": "كَانَ فِيهِ خُبْزٌ طَازَجٌ وَحَلِيبٌ.",
      "translation": "U njoj je bio svježi hljeb i mlijeko.",
      "translationEn": "In it there was fresh bread and milk.",
      "words": [
        {
          "w": "كَانَ",
          "lemma": "كَانَ يَكُونُ"
        },
        {
          "w": "خُبْزٌ",
          "lemma": "خُبْزٌ / أَخْبَازٌ"
        },
        {
          "w": "طَازَجٌ",
          "lemma": "طَازَجٌ"
        },
        {
          "w": "وَحَلِيبٌ",
          "lemma": "حَلِيبٌ"
        }
      ]
    },
    {
      "arabic": "سَأَلَ جِيرَانَهُ وَلَمْ يَعْرِفْ أَحَدٌ.",
      "translation": "Pitao je komšije ali niko nije znao.",
      "translationEn": "He asked his neighbours and no one knew.",
      "words": [
        {
          "w": "سَأَلَ",
          "lemma": "سَأَلَ يَسْأَلُ"
        },
        {
          "w": "جِيرَانَهُ",
          "lemma": "جَارٌ / جِيرَانٌ"
        },
        {
          "w": "يَعْرِفْ",
          "lemma": "عَرَفَ يَعْرِفُ"
        },
        {
          "w": "أَحَدٌ",
          "lemma": "أَحَدٌ"
        }
      ]
    },
    {
      "arabic": "بَعْدَ أُسْبُوعٍ رَأَى أُمَّهُ تَضَعُ الْكِيسَ فِي الصَّبَاحِ الْبَاكِرِ.",
      "translation": "Sedmicu kasnije vidio je majku kako stavlja vrećicu rano ujutro.",
      "translationEn": "A week later he saw his mother putting the bag early in the morning.",
      "words": [
        {
          "w": "أُسْبُوعٍ",
          "lemma": "أُسْبُوعٌ / أَسَابِيعُ"
        },
        {
          "w": "رَأَى",
          "lemma": "رَأَى يَرَى"
        },
        {
          "w": "تَضَعُ",
          "lemma": "وَضَعَ يَضَعُ"
        },
        {
          "w": "الْكِيسَ",
          "lemma": "كِيسٌ / أَكْيَاسٌ"
        },
        {
          "w": "الصَّبَاحِ",
          "lemma": "صَبَاحٌ / صَبَاحَاتٌ"
        },
        {
          "w": "الْبَاكِرِ",
          "lemma": "بَاكِرٌ"
        }
      ]
    },
    {
      "arabic": "عَرَفَ أَنَّهَا تَفْعَلُ هَذَا لِجِيرَانِهِمُ الْكِبَارِ.",
      "translation": "Shvatio je da to radi za njihove starije komšije.",
      "translationEn": "He realised that she did this for their elderly neighbours.",
      "words": [
        {
          "w": "عَرَفَ",
          "lemma": "عَرَفَ يَعْرِفُ"
        },
        {
          "w": "تَفْعَلُ",
          "lemma": "فَعَلَ يَفْعَلُ"
        },
        {
          "w": "لِجِيرَانِهِمُ",
          "lemma": "جَارٌ / جِيرَانٌ"
        },
        {
          "w": "الْكِبَارِ",
          "lemma": "كَبِيرٌ / كِبَارٌ"
        }
      ]
    }
  ],
  "metadata": {
    "difficulty": 1,
    "tags": [
      "mystery",
      "door",
      "food",
      "kindness",
      "mother"
    ]
  }
}