{
  "id": "mysteries-b1-011",
  "category": "mysteries",
  "level": "B1",
  "sentences": [
    {
      "arabic": "وَجَدَتْ هَنَاءُ وَرْدَةً حَمْرَاءَ عَلَى بَابِ غُرْفَتِهَا.",
      "translation": "Hana je pronašla crvenu ružu na vratima svoje sobe.",
      "translationEn": "Hana found a red rose on her bedroom door.",
      "words": [
        {
          "w": "وَجَدَتْ",
          "lemma": "وَجَدَ يَجِدُ"
        },
        {
          "w": "وَرْدَةً",
          "lemma": "وَرْدَةٌ / وَرْدَاتٌ"
        },
        {
          "w": "حَمْرَاءَ",
          "lemma": "أَحْمَرُ"
        },
        {
          "w": "غُرْفَتِهَا",
          "lemma": "غُرْفَةٌ / غُرَفٌ"
        }
      ]
    },
    {
      "arabic": "لَمْ تَعْرِفْ مَنْ وَضَعَهَا هُنَاكَ.",
      "translation": "Nije znala ko ju je tamo stavio.",
      "translationEn": "She did not know who had put it there.",
      "words": [
        {
          "w": "تَعْرِفْ",
          "lemma": "عَرَفَ يَعْرِفُ"
        },
        {
          "w": "وَضَعَهَا",
          "lemma": "وَضَعَ يَضَعُ"
        }
      ]
    },
    {
      "arabic": "سَأَلَتْ كُلَّ أَفْرَادِ عَائِلَتِهَا.",
      "translation": "Pitala je sve ukućane.",
      "translationEn": "She asked every member of her family.",
      "words": [
        {
          "w": "سَأَلَتْ",
          "lemma": "سَأَلَ يَسْأَلُ"
        },
        {
          "w": "أَفْرَادِ",
          "lemma": "فَرْدٌ / أَفْرَادٌ"
        },
        {
          "w": "عَائِلَتِهَا",
          "lemma": "عَائِلَةٌ / عَائِلَاتٌ"
        }
      ]
    },
    {
      "arabic": "قَالُوا جَمِيعًا: لَيْسَ نَحْنُ.",
      "translation": "Svi su rekli: Nismo mi.",
      "translationEn": "They all said: It was not us.",
      "words": [
        {
          "w": "قَالُوا",
          "lemma": "قَالَ يَقُولُ"
        }
      ]
    },
    {
      "arabic": "بَعْدَ يَوْمٍ اعْتَرَفَتْ صَدِيقَتُهَا بِأَنَّهَا وَضَعَتِ الْوَرْدَةَ.",
      "translation": "Dan nakon toga njena prijateljica je priznala da je stavila ružu.",
      "translationEn": "A day later her friend admitted that she had put the rose.",
      "words": [
        {
          "w": "اعْتَرَفَتْ",
          "lemma": "اعْتَرَفَ يَعْتَرِفُ"
        },
        {
          "w": "صَدِيقَتُهَا",
          "lemma": "صَدِيقَةٌ / صَدِيقَاتٌ"
        },
        {
          "w": "وَضَعَتِ",
          "lemma": "وَضَعَ يَضَعُ"
        },
        {
          "w": "الْوَرْدَةَ",
          "lemma": "وَرْدَةٌ / وَرْدَاتٌ"
        }
      ]
    }
  ],
  "metadata": {
    "difficulty": 1,
    "tags": [
      "mystery",
      "flower",
      "friend",
      "surprise"
    ]
  }
}
