{
  "id": "opinions-b1-039",
  "category": "opinions",
  "level": "B1",
  "sentences": [
    {
      "arabic": "أَعْتَقِدُ أَنَّ الْمَطَرَ نِعْمَةٌ يَجِبُ أَنْ نَشْكُرَ عَلَيْهَا.",
      "translation": "Smatram da je kiša blagodat za koju trebamo biti zahvalni.",
      "translationEn": "I believe that rain is a blessing we should be grateful for."
    },
    {
      "arabic": "الْمَطَرُ يُسْقِي الزُّرُوعَ وَيُنَظِّفُ الْهَوَاءَ.",
      "translation": "Kiša zaliva usjeve i čisti zrak.",
      "translationEn": "Rain waters the crops and cleans the air."
    },
    {
      "arabic": "أُحِبُّ أَنْ أَجْلِسَ وَأَسْمَعَ صَوْتَ الْمَطَرِ.",
      "translation": "Volim sjediti i slušati zvuk kiše.",
      "translationEn": "I like to sit and listen to the sound of rain."
    },
    {
      "arabic": "يَوْمُ الْمَطَرِ يَوْمٌ هَادِئٌ جَمِيلٌ لِلتَّأَمُّلِ.",
      "translation": "Kišni dan je miran i lijep dan za razmišljanje.",
      "translationEn": "A rainy day is a calm beautiful day for reflection."
    }
  ],
  "metadata": {
    "difficulty": 1,
    "tags": ["opinion", "rain", "nature", "gratitude"]
  }
}
