{
  "id": "literature-b2-140",
  "category": "literature",
  "level": "B2",
  "sentences": [
    {
      "arabic": "زُرْتُ الْمَكْتَبَةَ الْعَامَّةَ لِأَقْرَأَ كِتَابًا فِي الْأَدَبِ.",
      "translation": "Posjetio sam javnu biblioteku kako bih pročitao knjigu iz književnosti.",
      "translationEn": "I visited the public library to read a literature book."
    },
    {
      "arabic": "وَجَدْتُ رُفُوفًا مَلِيئَةً بِالرِّوَايَاتِ وَدَوَاوِينِ الشِّعْرِ.",
      "translation": "Pronašao sam police pune romana i zbirki poezije.",
      "translationEn": "I found shelves full of novels and poetry collections."
    },
    {
      "arabic": "جَلَسْتُ فِي هُدُوءٍ وَبَدَأْتُ الْقِرَاءَةَ.",
      "translation": "Sjeo sam u miru i počeo čitati.",
      "translationEn": "I sat in silence and started reading."
    },
    {
      "arabic": "كَانَتِ الْجُمَلُ سَهْلَةً وَوَاضِحَةً لِلْغَايَةِ.",
      "translation": "Rečenice su bile veoma lake i jasne.",
      "translationEn": "The sentences were very easy and clear."
    },
    {
      "arabic": "الْقِرَاءَةُ تُفَتِّحُ لَنَا أَبْوَابَ الْمَعْرِفَةِ وَالْخَيَالِ.",
      "translation": "Čitanje nam otvara vrata znanja i mašte.",
      "translationEn": "Reading opens the doors of knowledge and imagination for us."
    }
  ],
  "metadata": {
    "difficulty": 2,
    "tags": [
      "reading",
      "library",
      "literature"
    ]
  }
}