{
  "id": "social-b1-014",
  "category": "social",
  "level": "B1",
  "sentences": [
    {
      "arabic": "طَرَقَ وَلِيدٌ بَابَ جَارِهِ.",
      "translation": "Walid je pokucao na vrata komšije.",
      "translationEn": "Walid knocked on his neighbor's door.",
      "words": [
        {
          "w": "طَرَقَ",
          "lemma": "طَرَقَ يَطْرُقُ"
        },
        {
          "w": "بَابَ",
          "lemma": "بَابٌ / أَبْوَابٌ"
        },
        {
          "w": "جَارِهِ"
        }
      ]
    },
    {
      "arabic": "طَلَبَ مِنْهُ قَهْوَةً صَغِيرَةً.",
      "translation": "Zatražio je od njega malo kafe.",
      "translationEn": "He asked him for a little coffee.",
      "words": [
        {
          "w": "طَلَبَ",
          "lemma": "طَلَبَ يَطْلُبُ"
        },
        {
          "w": "قَهْوَةً",
          "lemma": "قَهْوَةٌ / قَهَوَاتٌ"
        },
        {
          "w": "صَغِيرَةً",
          "lemma": "صَغِيرٌ / صِغَارٌ"
        }
      ]
    },
    {
      "arabic": "أَعْطَاهُ الجَارُ القَهْوَةَ وَابْتَسَمَ.",
      "translation": "Komšija mu je dao kafu i nasmiješio se.",
      "translationEn": "The neighbor gave him the coffee and smiled.",
      "words": [
        {
          "w": "أَعْطَاهُ",
          "lemma": "أَعْطَى يُعْطِي"
        },
        {
          "w": "الجَارُ",
          "lemma": "جَارٌ / جِيرَانٌ"
        },
        {
          "w": "القَهْوَةَ"
        },
        {
          "w": "وَابْتَسَمَ",
          "lemma": "اِبْتَسَمَ يَبْتَسِمُ"
        }
      ]
    },
    {
      "arabic": "شَكَرَهُ وَعَدَ أَنْ يُعِيدَ لَهُ ذَلِكَ.",
      "translation": "Zahvalio mu je i obećao da će mu uzvratiti.",
      "translationEn": "He thanked him and promised to return the favor.",
      "words": [
        {
          "w": "شَكَرَهُ",
          "lemma": "شَكَرَ يَشْكُرُ"
        },
        {
          "w": "وَعَدَ",
          "lemma": "وَعَدَ يَعِدُ"
        },
        {
          "w": "يُعِيدَ"
        }
      ]
    }
  ],
  "metadata": {
    "difficulty": 1,
    "tags": [
      "neighbors",
      "borrowing",
      "kindness"
    ]
  }
}