{
  "items": [
    {
      "id": "travel-b1-001",
      "arabic": "سَافَرَتِ الْعَائِلَةُ إِلَى مَدِينَةٍ جَمِيلَةٍ عَلَى الْبَحْرِ.",
      "metadata": {
        "difficulty": 1,
        "tags": [
          "family",
          "sea",
          "hotel"
        ]
      }
    },
    {
      "id": "travel-b1-002",
      "arabic": "وَصَلَ الْقِطَارُ إِلَى الْمَحَطَّةِ فِي الصَّبَاحِ.",
      "metadata": {
        "difficulty": 1,
        "tags": [
          "train",
          "station",
          "taxi"
        ]
      }
    },
    {
      "id": "travel-b1-003",
      "arabic": "سَأَلَ عُمَرُ رَجُلًا عَنِ الطَّرِيقِ إِلَى الْمَتْحَفِ.",
      "metadata": {
        "difficulty": 1,
        "tags": [
          "directions",
          "museum",
          "city"
        ]
      }
    },
    {
      "id": "travel-b1-004",
      "arabic": "اشْتَرَى خَالِدٌ تَذْكِرَةَ الْقِطَارِ مِنَ الشِّبَّاكِ.",
      "metadata": {
        "difficulty": 1,
        "tags": [
          "train",
          "ticket",
          "journey"
        ]
      }
    },
    {
      "id": "travel-b1-005",
      "arabic": "رَأَى يُوسُفُ الْبَحْرَ لِأَوَّلِ مَرَّةٍ فِي حَيَاتِهِ.",
      "metadata": {
        "difficulty": 1,
        "tags": [
          "sea",
          "beach",
          "first time"
        ]
      }
    },
    {
      "id": "travel-b1-006",
      "arabic": "رَكِبَتِ الْعَائِلَةُ الْحَافِلَةَ إِلَى وَسَطِ الْمَدِينَةِ.",
      "metadata": {
        "difficulty": 1,
        "tags": [
          "bus",
          "city center",
          "family"
        ]
      }
    },
    {
      "id": "travel-b1-007",
      "arabic": "حَجَزَ سَمِيرٌ غُرْفَةً فِي الْفُنْدُقِ عَبْرَ الْهَاتِفِ.",
      "metadata": {
        "difficulty": 1,
        "tags": [
          "hotel",
          "reservation",
          "room"
        ]
      }
    },
    {
      "id": "travel-b1-008",
      "arabic": "زَارَتْ مَرْيَمُ سُوقَ الْمَدِينَةِ الْقَدِيمَةِ مَعَ أُخْتِهَا.",
      "metadata": {
        "difficulty": 1,
        "tags": [
          "market",
          "shopping",
          "old city"
        ]
      }
    },
    {
      "id": "travel-b1-009",
      "arabic": "سَافَرَ مُحَمَّدٌ بِالطَّائِرَةِ لِأَوَّلِ مَرَّةٍ.",
      "metadata": {
        "difficulty": 1,
        "tags": [
          "airplane",
          "first time",
          "travel"
        ]
      }
    },
    {
      "id": "travel-b1-010",
      "arabic": "أَرَادَتِ الْعَائِلَةُ أَنْ تَزُورَ الْجِبَالَ فِي الشَّمَالِ.",
      "metadata": {
        "difficulty": 1,
        "tags": [
          "mountains",
          "car",
          "nature"
        ]
      }
    },
    {
      "id": "travel-b1-011",
      "arabic": "سَأَلَتْ فَاطِمَةُ الشُّرْطِيَّ عَنِ الطَّرِيقِ إِلَى الْمَطَارِ.",
      "metadata": {
        "difficulty": 1,
        "tags": [
          "airport",
          "bus",
          "directions"
        ]
      }
    },
    {
      "id": "travel-b1-012",
      "arabic": "وَصَلَ الْوَلَدُ إِلَى الشَّاطِئِ مَعَ أَبِيهِ.",
      "metadata": {
        "difficulty": 1,
        "tags": [
          "beach",
          "sand",
          "children"
        ]
      }
    },
    {
      "id": "travel-b1-013",
      "arabic": "ذَهَبَتِ الْمَجْمُوعَةُ إِلَى مَطْعَمٍ فِي وَسَطِ الْمَدِينَةِ.",
      "metadata": {
        "difficulty": 1,
        "tags": [
          "restaurant",
          "local food",
          "city"
        ]
      }
    },
    {
      "id": "travel-b1-014",
      "arabic": "اشْتَرَى عَلِيٌّ خَرِيطَةَ الْمَدِينَةِ مِنَ الدُّكَّانِ.",
      "metadata": {
        "difficulty": 1,
        "tags": [
          "map",
          "museum",
          "city"
        ]
      }
    },
    {
      "id": "travel-b1-015",
      "arabic": "جَلَسَتِ الْعَائِلَةُ فِي الْحَدِيقَةِ بَعْدَ يَوْمٍ طَوِيلٍ.",
      "metadata": {
        "difficulty": 1,
        "tags": [
          "park",
          "family",
          "evening"
        ]
      }
    },
    {
      "id": "travel-b1-016",
      "arabic": "رَكِبَ الطِّفْلُ الْحَافِلَةَ لِأَوَّلِ مَرَّةٍ مَعَ جَدِّهِ.",
      "metadata": {
        "difficulty": 1,
        "tags": [
          "bus",
          "grandfather",
          "children"
        ]
      }
    },
    {
      "id": "travel-b1-017",
      "arabic": "وَصَلَتِ الْعَائِلَةُ إِلَى الْفُنْدُقِ لَيْلًا.",
      "metadata": {
        "difficulty": 1,
        "tags": [
          "hotel",
          "night",
          "family"
        ]
      }
    },
    {
      "id": "travel-b1-018",
      "arabic": "زَارَ حَسَنٌ مَدِينَةً تَارِيخِيَّةً قَدِيمَةً.",
      "metadata": {
        "difficulty": 1,
        "tags": [
          "historical city",
          "mosque",
          "photos"
        ]
      }
    },
    {
      "id": "travel-b1-019",
      "arabic": "أَرَادَ سَعِيدٌ أَنْ يَشْتَرِيَ تَذْكِرَةَ الْحَافِلَةِ.",
      "metadata": {
        "difficulty": 1,
        "tags": [
          "bus",
          "ticket",
          "transport"
        ]
      }
    },
    {
      "id": "travel-b1-020",
      "arabic": "أَحَبَّتْ رَنَا مَدِينَةَ الْإِسْكَنْدَرِيَّةَ كَثِيرًا.",
      "metadata": {
        "difficulty": 1,
        "tags": [
          "Alexandria",
          "sea",
          "seafood"
        ]
      }
    },
    {
      "id": "travel-b1-021",
      "arabic": "رَكِبَتِ الْأُسْرَةُ الْقِطَارَ إِلَى الْقَرْيَةِ.",
      "metadata": {
        "difficulty": 1,
        "tags": [
          "train",
          "village",
          "family"
        ]
      }
    },
    {
      "id": "travel-b1-022",
      "arabic": "وَقَفَتِ الْأُمُّ أَمَامَ خَرِيطَةِ الْمَدِينَةِ عَلَى الْجِدَارِ.",
      "metadata": {
        "difficulty": 1,
        "tags": [
          "map",
          "park",
          "family"
        ]
      }
    },
    {
      "id": "travel-b1-023",
      "arabic": "وَصَلَ الرَّكَّابُ إِلَى الْمَطَارِ فِي الصَّبَاحِ الْبَاكِرِ.",
      "metadata": {
        "difficulty": 1,
        "tags": [
          "airport",
          "airplane",
          "departure"
        ]
      }
    },
    {
      "id": "travel-b1-024",
      "arabic": "كَانَ نُورٌ يُحِبُّ السَّفَرَ إِلَى أَمَاكِنَ جَدِيدَةٍ.",
      "metadata": {
        "difficulty": 1,
        "tags": [
          "travel",
          "planning",
          "city"
        ]
      }
    },
    {
      "id": "travel-b1-025",
      "arabic": "تَعَبَتِ الْبِنْتُ مِنَ الْمَشْيِ وَجَلَسَتْ عَلَى الْمَقْعَدِ.",
      "metadata": {
        "difficulty": 1,
        "tags": [
          "children",
          "walking",
          "rest"
        ]
      }
    },
    {
      "id": "travel-b1-026",
      "arabic": "دَخَلَتِ الْعَائِلَةُ إِلَى مَتْحَفٍ كَبِيرٍ فِي الْمَدِينَةِ.",
      "metadata": {
        "difficulty": 1,
        "tags": [
          "museum",
          "family",
          "history"
        ]
      }
    },
    {
      "id": "travel-b1-027",
      "arabic": "أَخَذَ طَارِقٌ سَيَّارَةَ الْأُجْرَةِ إِلَى وَسَطِ الْمَدِينَةِ.",
      "metadata": {
        "difficulty": 1,
        "tags": [
          "taxi",
          "city",
          "market"
        ]
      }
    },
    {
      "id": "travel-b1-028",
      "arabic": "نَسِيَ كَرِيمٌ حَقِيبَتَهُ فِي الْحَافِلَةِ.",
      "metadata": {
        "difficulty": 1,
        "tags": [
          "bus",
          "lost bag",
          "city"
        ]
      }
    },
    {
      "id": "travel-b1-029",
      "arabic": "وَقَفَتِ الْعَائِلَةُ عَلَى جِسْرٍ فَوْقَ النَّهْرِ.",
      "metadata": {
        "difficulty": 1,
        "tags": [
          "bridge",
          "river",
          "family photo"
        ]
      }
    },
    {
      "id": "travel-b1-030",
      "arabic": "بَحَثَ إِبْرَاهِيمُ عَنْ فُنْدُقٍ رَخِيصٍ فِي الْمَدِينَةِ.",
      "metadata": {
        "difficulty": 1,
        "tags": [
          "hotel",
          "budget",
          "room"
        ]
      }
    },
    {
      "id": "travel-b1-031",
      "arabic": "رَأَى الطِّفْلُ غَرِيبًا وَسَأَلَ أَبَاهُ عَنْهُ.",
      "metadata": {
        "difficulty": 1,
        "tags": [
          "children",
          "kindness",
          "city"
        ]
      }
    },
    {
      "id": "travel-b1-032",
      "arabic": "وَصَلَ الْقِطَارُ مُتَأَخِّرًا بِسَبَبِ الطَّقْسِ السَّيِّئِ.",
      "metadata": {
        "difficulty": 1,
        "tags": [
          "train",
          "delay",
          "station"
        ]
      }
    },
    {
      "id": "travel-b1-033",
      "arabic": "زَارَ الطُّلَّابُ مَدِينَةً قَدِيمَةً مَعَ مُعَلِّمِهِمْ.",
      "metadata": {
        "difficulty": 1,
        "tags": [
          "students",
          "school trip",
          "history"
        ]
      }
    },
    {
      "id": "travel-b1-034",
      "arabic": "كَانَ الطَّقْسُ حَارًّا حِينَ وَصَلُوا إِلَى الْمَدِينَةِ.",
      "metadata": {
        "difficulty": 1,
        "tags": [
          "hot weather",
          "cafe",
          "city walk"
        ]
      }
    },
    {
      "id": "travel-b1-035",
      "arabic": "أَرَادَتْ لَيْلَى أَنْ تَرَى غُرُوبَ الشَّمْسِ عَلَى الْبَحْرِ.",
      "metadata": {
        "difficulty": 1,
        "tags": [
          "sunset",
          "beach",
          "beauty"
        ]
      }
    },
    {
      "id": "travel-b1-036",
      "arabic": "سَافَرَ جَابِرٌ إِلَى بَلَدٍ عَرَبِيٍّ لِزِيَارَةِ صَدِيقِهِ.",
      "metadata": {
        "difficulty": 1,
        "tags": [
          "friendship",
          "welcome",
          "Arab country"
        ]
      }
    },
    {
      "id": "travel-b1-037",
      "arabic": "أَعَدَّتِ الْأُمُّ الْحَقَائِبَ قَبْلَ يَوْمٍ مِنَ السَّفَرِ.",
      "metadata": {
        "difficulty": 1,
        "tags": [
          "packing",
          "preparation",
          "family"
        ]
      }
    },
    {
      "id": "travel-b1-038",
      "arabic": "وَصَلَ الْمُسَافِرُونَ إِلَى الْمَدِينَةِ وَطَلَبُوا دَلِيلًا سِيَاحِيًّا.",
      "metadata": {
        "difficulty": 1,
        "tags": [
          "tourist guide",
          "museum",
          "city"
        ]
      }
    },
    {
      "id": "travel-b1-039",
      "arabic": "قَرَّرَ صَالِحٌ أَنْ يُسَافِرَ بِالسَّيَّارَةِ إِلَى الشَّمَالِ.",
      "metadata": {
        "difficulty": 1,
        "tags": [
          "road trip",
          "car",
          "north"
        ]
      }
    },
    {
      "id": "travel-b1-040",
      "arabic": "أَحَبَّ الْأَطْفَالُ الشَّاطِئَ وَلَعِبُوا فِيهِ كَثِيرًا.",
      "metadata": {
        "difficulty": 1,
        "tags": [
          "children",
          "beach",
          "play"
        ]
      }
    },
    {
      "id": "travel-b1-041",
      "arabic": "غَادَرَتِ الْعَائِلَةُ الْفُنْدُقَ فِي الصَّبَاحِ.",
      "metadata": {
        "difficulty": 1,
        "tags": [
          "farewell",
          "hotel",
          "memories"
        ]
      }
    },
    {
      "id": "travel-b1-042",
      "arabic": "سَأَلَ رَجُلٌ عَجُوزٌ مُحَمَّدًا عَنِ اسْمِ الْفُنْدُقِ.",
      "metadata": {
        "difficulty": 1,
        "tags": [
          "kindness",
          "hotel",
          "city"
        ]
      }
    },
    {
      "id": "travel-b1-043",
      "arabic": "وَجَدَتْ سُعَادُ مَقْهًى صَغِيرًا بِجَانِبِ الْبَحْرِ.",
      "metadata": {
        "difficulty": 1,
        "tags": [
          "cafe",
          "sea",
          "relaxation"
        ]
      }
    },
    {
      "id": "travel-b1-044",
      "arabic": "أَخَذَتِ الرِّيحُ قُبَّعَةَ الطِّفْلِ عَلَى الشَّاطِئِ.",
      "metadata": {
        "difficulty": 1,
        "tags": [
          "children",
          "beach",
          "funny"
        ]
      }
    },
    {
      "id": "travel-b1-045",
      "arabic": "فِي آخِرِ يَوْمٍ جَمَعَتِ الْعَائِلَةُ ذِكْرَيَاتِهَا.",
      "metadata": {
        "difficulty": 1,
        "tags": [
          "memories",
          "family",
          "holiday"
        ]
      }
    }
  ]
}