{
  "id": "travel-b1-036",
  "category": "travel",
  "level": "B1",
  "sentences": [
    {
      "arabic": "سَافَرَ جَابِرٌ إِلَى بَلَدٍ عَرَبِيٍّ لِزِيَارَةِ صَدِيقِهِ.",
      "translation": "Jabir je putovao u arapsku zemlju da posjeti prijatelja.",
      "translationEn": "Jabir traveled to an Arab country to visit his friend.",
      "words": [
        {
          "w": "سَافَرَ",
          "lemma": "سَافَرَ يُسَافِرُ"
        },
        {
          "w": "بَلَدٍ",
          "lemma": "بَلَدٌ / بِلَادٌ"
        },
        {
          "w": "عَرَبِيٍّ",
          "lemma": "عَرَبِيٌّ"
        },
        {
          "w": "زِيَارَةِ",
          "lemma": "زِيَارَةٌ / زِيَارَاتٌ"
        }
      ]
    },
    {
      "arabic": "اسْتَقْبَلَهُ الصَّدِيقُ فِي الْمَطَارِ وَرَحَّبَ بِهِ.",
      "translation": "Prijatelj ga je dočekao na aerodromu i toplo pozdravio.",
      "translationEn": "His friend received him at the airport and welcomed him.",
      "words": [
        {
          "w": "اسْتَقْبَلَهُ",
          "lemma": "اِسْتَقْبَلَ يَسْتَقْبِلُ"
        },
        {
          "w": "الْمَطَارِ",
          "lemma": "مَطَارٌ / مَطَارَاتٌ"
        },
        {
          "w": "رَحَّبَ",
          "lemma": "رَحَّبَ يُرَحِّبُ"
        }
      ]
    },
    {
      "arabic": "أَخَذَهُ إِلَى الْبَيْتِ وَقَدَّمَ لَهُ الطَّعَامَ.",
      "translation": "Odveo ga je kući i ponudio ga hranom.",
      "translationEn": "He took him home and offered him food.",
      "words": [
        {
          "w": "أَخَذَهُ",
          "lemma": "أَخَذَ يَأْخُذُ"
        },
        {
          "w": "قَدَّمَ",
          "lemma": "قَدَّمَ يُقَدِّمُ"
        },
        {
          "w": "الطَّعَامَ",
          "lemma": "طَعَامٌ / أَطْعِمَةٌ"
        }
      ]
    },
    {
      "arabic": "شَعَرَ جَابِرٌ بِالدِّفْءِ وَالتَّرْحِيبِ.",
      "translation": "Jabir je osjetio toplinu i dobrodošlicu.",
      "translationEn": "Jabir felt warmth and welcome.",
      "words": [
        {
          "w": "شَعَرَ",
          "lemma": "شَعَرَ يَشْعُرُ"
        },
        {
          "w": "الدِّفْءِ",
          "lemma": "دِفْءٌ"
        },
        {
          "w": "التَّرْحِيبِ",
          "lemma": "تَرْحِيبٌ"
        }
      ]
    }
  ],
  "metadata": {
    "difficulty": 1,
    "tags": [
      "friendship",
      "welcome",
      "Arab country"
    ]
  }
}
