{
  "id": "work-b1-027",
  "category": "work",
  "level": "B1",
  "sentences": [
    {
      "arabic": "تَعْمَلُ سَمِيَّةُ طَبِيبَةً فِي مُسْتَشْفَى قَرِيبٍ مِنَ الْبَيْتِ.",
      "translation": "Samija radi kao ljekarica u bolnici blizu kuće.",
      "translationEn": "Samiyya works as a doctor in a hospital near her home."
    },
    {
      "arabic": "تُفَحِّصُ الْمَرْضَى فِي الصَّبَاحِ وَتَكْتُبُ الْوَصَفَاتِ.",
      "translation": "Ujutro pregledava pacijente i piše recepte.",
      "translationEn": "She examines patients in the morning and writes prescriptions."
    },
    {
      "arabic": "تَأْكُلُ غَدَاءَهَا مَعَ الزُّمَلَاءِ فِي الِاسْتِرَاحَةِ.",
      "translation": "Ručava s kolegama u pauzi.",
      "translationEn": "She has lunch with colleagues during the break."
    },
    {
      "arabic": "تَشْعُرُ بِالرِّضَا حِينَ يَخْرُجُ الْمَرِيضُ بِصِحَّةٍ جَيِّدَةٍ.",
      "translation": "Osjeća zadovoljstvo kad pacijent izađe zdravo.",
      "translationEn": "She feels satisfied when a patient leaves in good health."
    }
  ],
  "metadata": {
    "difficulty": 1,
    "tags": ["doctor", "hospital", "patients", "work routine"]
  }
}
