{
  "id": "history-b1-007",
  "category": "history",
  "level": "B1",
  "sentences": [
    {
      "arabic": "كَانَ السُّوقُ الْقَدِيمُ مَكَانًا مُزْدَحِمًا وَصَاخِبًا.",
      "translation": "Stara tržnica bila je gužvovito i bučno mjesto.",
      "translationEn": "The old market was a busy and noisy place.",
      "words": [
        {
          "w": "كَانَ",
          "lemma": "كَانَ يَكُونُ"
        },
        {
          "w": "السُّوقُ",
          "lemma": "سُوقٌ / أَسْوَاقٌ"
        },
        {
          "w": "الْقَدِيمُ",
          "lemma": "قَدِيمٌ"
        },
        {
          "w": "مَكَانًا",
          "lemma": "مَكَانٌ / أَمَاكِنُ"
        },
        {
          "w": "مُزْدَحِمًا",
          "lemma": "مُزْدَحِمٌ"
        },
        {
          "w": "وَصَاخِبًا",
          "lemma": "صَاخِبٌ"
        }
      ]
    },
    {
      "arabic": "بَاعَ النَّاسُ الْفَوَاكِهَ وَالْخُضَرَ وَالْقُمَاشَ.",
      "translation": "Ljudi su prodavali voće, povrće i tkanine.",
      "translationEn": "People sold fruits, vegetables, and fabrics.",
      "words": [
        {
          "w": "بَاعَ",
          "lemma": "بَاعَ يَبِيعُ"
        },
        {
          "w": "النَّاسُ",
          "lemma": "نَاسٌ"
        },
        {
          "w": "الْفَوَاكِهَ",
          "lemma": "فَاكِهَةٌ / فَوَاكِهُ"
        },
        {
          "w": "وَالْخُضَرَ",
          "lemma": "خُضَرٌ / خَضْرَاوَاتٌ"
        },
        {
          "w": "وَالْقُمَاشَ",
          "lemma": "قُمَاشٌ / أَقْمِشَةٌ"
        }
      ]
    },
    {
      "arabic": "كَانَ الْجَمِيعُ يَتَكَلَّمُ بِصَوْتٍ عَالٍ فِي السُّوقِ.",
      "translation": "Svi su govorili glasno na tržnici.",
      "translationEn": "Everyone spoke loudly in the market.",
      "words": [
        {
          "w": "كَانَ",
          "lemma": "كَانَ يَكُونُ"
        },
        {
          "w": "يَتَكَلَّمُ",
          "lemma": "تَكَلَّمَ يَتَكَلَّمُ"
        },
        {
          "w": "بِصَوْتٍ",
          "lemma": "صَوْتٌ / أَصْوَاتٌ"
        },
        {
          "w": "عَالٍ",
          "lemma": "عَالٍ"
        },
        {
          "w": "السُّوقِ",
          "lemma": "سُوقٌ / أَسْوَاقٌ"
        }
      ]
    },
    {
      "arabic": "كَانَ الْأَطْفَالُ يُحِبُّونَ الذَّهَابَ إِلَى السُّوقِ.",
      "translation": "Djeca su voljela ići na tržnicu.",
      "translationEn": "The children loved going to the market.",
      "words": [
        {
          "w": "كَانَ",
          "lemma": "كَانَ يَكُونُ"
        },
        {
          "w": "الْأَطْفَالُ",
          "lemma": "طِفْلٌ / أَطْفَالٌ"
        },
        {
          "w": "يُحِبُّونَ",
          "lemma": "أَحَبَّ يُحِبُّ"
        },
        {
          "w": "الذَّهَابَ",
          "lemma": "ذَهَابٌ"
        },
        {
          "w": "السُّوقِ",
          "lemma": "سُوقٌ / أَسْوَاقٌ"
        }
      ]
    }
  ],
  "metadata": {
    "difficulty": 1,
    "tags": [
      "market",
      "trade",
      "daily life"
    ]
  }
}