{
  "id": "technology-b2-196",
  "category": "technology",
  "level": "B2",
  "sentences": [
    {
      "arabic": "تُعْتَبَرُ الْهَوَاتِفُ الذَّكِيَّةُ مُهِمَّةً جِدًّا فِي حَيَاتِنَا الْيَوْمِيَّةِ.",
      "translation": "Pametni telefoni se smatraju veoma važnim u našem svakodnevnom životu.",
      "translationEn": "Smartphones are considered very important in our daily lives.",
      "words": [
        {
          "w": "جِدًّا",
          "lemma": "جِدًّا"
        }
      ]
    },
    {
      "arabic": "يَسْتَخْدِمُهَا النَّاسُ لِلتَّحَدُّثِ مَعَ أَصْدِقَائِهِمْ وَالْبَحْثِ عَنِ الْمَعْلُومَاتِ.",
      "translation": "Ljudi ih koriste za razgovor s prijateljima i traženje informacija.",
      "translationEn": "People use them to talk with their friends and search for information.",
      "words": []
    },
    {
      "arabic": "تُسَاعِدُنَا هَذِهِ الْأَجْهِزَةُ الصَّغِيرَةُ فِي تَنْظِيمِ وَقْتِنَا وَأَعْمَالِنَا.",
      "translation": "Ovi mali uređaji nam pomažu u organizaciji našeg vremena i poslova.",
      "translationEn": "These small devices help us organize our time and work.",
      "words": []
    }
  ],
  "metadata": {
    "difficulty": 2,
    "tags": [
      "smartphones",
      "daily life",
      "communication"
    ]
  }
}