{
  "id": "health-b1-078",
  "category": "health",
  "level": "B1",
  "sentences": [
    {
      "arabic": "ذَهَبْتُ إِلَى الصَّيْدَلِيَّةِ أَمْسِ لِأَشْتَرِيَ دَوَاءً لِلصُّدَاعِ.",
      "translation": "Jučer sam otišao u apoteku da kupim lijek za glavobolju.",
      "translationEn": "I went to the pharmacy yesterday to buy medicine for a headache."
    },
    {
      "arabic": "شَرَحَ لِي الصَّيْدَلَانِيُّ كَيْفِيَّةَ اسْتِخْدَامِ الدَّوَاءِ بِشَكْلٍ صَحِيحٍ.",
      "translation": "Farmaceut mi je objasnio kako da pravilno koristim lijek.",
      "translationEn": "The pharmacist explained to me how to use the medicine correctly."
    },
    {
      "arabic": "تَنَاوَلْتُ الدَّوَاءَ بَعْدَ الْغَدَاءِ وَشَعَرْتُ بِتَحَسُّنٍ سَرِيعٍ.",
      "translation": "Popio sam lijek nakon ručka i osjetio brzo poboljšanje.",
      "translationEn": "I took the medicine after lunch and felt a quick improvement."
    }
  ],
  "metadata": {
    "difficulty": 1,
    "tags": [
      "pharmacy",
      "medicine",
      "treatment"
    ]
  }
}